__init__.py
pestuary_cli.py
pestuary/__init__.py
pestuary/autoretrieve.py
pestuary/collections.py
pestuary/content.py
pestuary/pestuary.py
pestuary/pinning.py
pestuary/utils/__init__.py
pestuary/utils/utils.py
pestuary/versioned_uploads/__init__.py
pestuary/versioned_uploads/versioned_uploads.py
pestuary-1.0.15.dist-info/LICENSE
pestuary-1.0.15.dist-info/METADATA
pestuary-1.0.15.dist-info/WHEEL
pestuary-1.0.15.dist-info/entry_points.txt
pestuary-1.0.15.dist-info/top_level.txt
pestuary-1.0.15.dist-info/RECORD
