Metadata-Version: 2.1
Name: pestuary
Version: 1.0.15
License-File: LICENSE
Requires-Dist: estuary-client
Requires-Dist: requests
Requires-Dist: instantcli
